{
  "Top": "crypto_sign",
  "RtlTop": "crypto_sign",
  "RtlPrefix": "",
  "SourceLanguage": "c",
  "ResetStyle": "control",
  "GenerateBdFiles": "0",
  "HostMachineBits": "64",
  "Target": {
    "Family": "artix7",
    "Device": "xc7a200t",
    "Package": "-fbg676",
    "Speed": "-2"
  },
  "HlsSolution": {
    "Config": [
      "config_sdx -optimization_level=none",
      "config_sdx -target=none",
      "config_export -vivado_optimization_level=2"
    ],
    "DirectiveTcl": [
      "set_directive_top crypto_sign -name crypto_sign",
      "set_directive_top crypto_sign -name crypto_sign",
      "set_directive_top crypto_sign -name crypto_sign",
      "set_directive_top crypto_sign -name crypto_sign",
      "set_directive_top crypto_sign -name crypto_sign",
      "set_directive_top crypto_sign -name crypto_sign",
      "set_directive_top crypto_sign -name crypto_sign",
      "set_directive_top crypto_sign -name crypto_sign",
      "set_directive_top crypto_sign -name crypto_sign",
      "set_directive_top crypto_sign -name crypto_sign",
      "set_directive_top crypto_sign -name crypto_sign",
      "set_directive_top crypto_sign -name crypto_sign",
      "set_directive_top crypto_sign -name crypto_sign"
    ],
    "DirectiveInfo": [
      "top crypto_sign {{name crypto_sign}} {}",
      "top crypto_sign {{name crypto_sign}} {}",
      "top crypto_sign {{name crypto_sign}} {}",
      "top crypto_sign {{name crypto_sign}} {}",
      "top crypto_sign {{name crypto_sign}} {}",
      "top crypto_sign {{name crypto_sign}} {}",
      "top crypto_sign {{name crypto_sign}} {}",
      "top crypto_sign {{name crypto_sign}} {}",
      "top crypto_sign {{name crypto_sign}} {}",
      "top crypto_sign {{name crypto_sign}} {}",
      "top crypto_sign {{name crypto_sign}} {}",
      "top crypto_sign {{name crypto_sign}} {}",
      "top crypto_sign {{name crypto_sign}} {}"
    ]
  },
  "Args": {
    "sm": {
      "index": "0",
      "type": {
        "kinds": ["array"],
        "dataType": "unsigned",
        "dataWidth": "8",
        "arraySizes": ["5720"],
        "multiInterfaceRef": [
          "sm_address0",
          "sm_address1",
          "sm_d0",
          "sm_d1",
          "sm_q0",
          "sm_q1"
        ]
      }
    },
    "smlen": {
      "index": "1",
      "type": {
        "kinds": ["pointer"],
        "dataType": "long",
        "dataWidth": "64",
        "interfaceRef": "smlen"
      }
    },
    "m": {
      "index": "2",
      "type": {
        "kinds": ["array"],
        "dataType": "unsigned",
        "dataWidth": "8",
        "arraySizes": ["3300"],
        "multiInterfaceRef": [
          "m_address0",
          "m_q0"
        ]
      }
    },
    "mlen": {
      "index": "3",
      "type": {
        "dataType": "long",
        "dataWidth": "64",
        "interfaceRef": "mlen"
      }
    },
    "sk": {
      "index": "4",
      "type": {
        "kinds": ["array"],
        "dataType": "unsigned",
        "dataWidth": "8",
        "arraySizes": ["2544"],
        "multiInterfaceRef": [
          "sk_address0",
          "sk_address1",
          "sk_q0",
          "sk_q1"
        ]
      }
    }
  },
  "Return": {
    "dataType": "int",
    "dataWidth": "32",
    "interfaceRef": "ap_return"
  },
  "ClockInfo": {
    "ClockName": "ap_clk",
    "ClockPeriod": "10000",
    "IsCombLogic": "0",
    "II": "x",
    "Latency": "undef",
    "Uncertainty": "1250"
  },
  "Xdc": {"OocClocks": ["create_clock -name ap_clk -period 10000.000 [get_ports ap_clk]"]},
  "Ipx": {
    "Vendor": "xilinx.com",
    "Library": "hls",
    "Name": "crypto_sign",
    "Version": "1.0",
    "DisplayName": "Crypto_sign",
    "Revision": "",
    "Description": "An IP generated by Vivado HLS",
    "Taxonomy": "\/VIVADO_HLS_IP",
    "AutoFamilySupport": ""
  },
  "Files": {
    "CSource": [
      "..\/..\/aes.c",
      "..\/..\/aes256ctr.c",
      "..\/..\/fips202.c",
      "..\/..\/ntt.c",
      "..\/..\/packing.c",
      "..\/..\/poly.c",
      "..\/..\/polyvec.c",
      "..\/..\/reduce.c",
      "..\/..\/rng.c",
      "..\/..\/rounding.c",
      "..\/..\/sign.c",
      "..\/..\/symmetric-aes.c",
      "..\/..\/symmetric-shake.c"
    ],
    "Vhdl": [
      "impl\/vhdl\/crypto_sign_mac_mhbi.vhd",
      "impl\/vhdl\/crypto_sign_mac_mjbC.vhd",
      "impl\/vhdl\/crypto_sign_mac_mkbM.vhd",
      "impl\/vhdl\/crypto_sign_urem_dEe.vhd",
      "impl\/vhdl\/keccak_absorb.vhd",
      "impl\/vhdl\/keccak_absorb_2.vhd",
      "impl\/vhdl\/keccak_absorb_2_t.vhd",
      "impl\/vhdl\/keccak_absorb_3199.vhd",
      "impl\/vhdl\/keccak_squeezeblocks.vhd",
      "impl\/vhdl\/keccak_squeezeblocks_1.vhd",
      "impl\/vhdl\/keccak_squeezeblocks_2.vhd",
      "impl\/vhdl\/KeccakF1600_StatePer.vhd",
      "impl\/vhdl\/KeccakF1600_StatePer_1.vhd",
      "impl\/vhdl\/pqcrystals_dilithbkb.vhd",
      "impl\/vhdl\/pqcrystals_dilithcud.vhd",
      "impl\/vhdl\/pqcrystals_dilitheOg.vhd",
      "impl\/vhdl\/pqcrystals_dilithfYi.vhd",
      "impl\/vhdl\/pqcrystals_dilithium.vhd",
      "impl\/vhdl\/pqcrystals_dilithium_1.vhd",
      "impl\/vhdl\/pqcrystals_dilithium_2.vhd",
      "impl\/vhdl\/pqcrystals_dilithium_3.vhd",
      "impl\/vhdl\/pqcrystals_dilithium_4.vhd",
      "impl\/vhdl\/pqcrystals_dilithium_5.vhd",
      "impl\/vhdl\/pqcrystals_dilithium_6.vhd",
      "impl\/vhdl\/pqcrystals_dilithium_7.vhd",
      "impl\/vhdl\/pqcrystals_dilithium_8.vhd",
      "impl\/vhdl\/pqcrystals_dilithium_9.vhd",
      "impl\/vhdl\/pqcrystals_dilithium_10.vhd",
      "impl\/vhdl\/pqcrystals_dilithium_11.vhd",
      "impl\/vhdl\/pqcrystals_dilithium_12.vhd",
      "impl\/vhdl\/pqcrystals_dilithium_13.vhd",
      "impl\/vhdl\/pqcrystals_dilithium_14.vhd",
      "impl\/vhdl\/pqcrystals_dilithium_15.vhd",
      "impl\/vhdl\/pqcrystals_dilithium_16.vhd",
      "impl\/vhdl\/pqcrystals_dilithium_17.vhd",
      "impl\/vhdl\/pqcrystals_dilithium_18.vhd",
      "impl\/vhdl\/pqcrystals_dilithium_19.vhd",
      "impl\/vhdl\/pqcrystals_dilithium_20.vhd",
      "impl\/vhdl\/pqcrystals_dilithium_21.vhd",
      "impl\/vhdl\/pqcrystals_dilithium_22.vhd",
      "impl\/vhdl\/pqcrystals_dilithium_23.vhd",
      "impl\/vhdl\/pqcrystals_dilithium_24.vhd",
      "impl\/vhdl\/pqcrystals_dilithium_25.vhd",
      "impl\/vhdl\/pqcrystals_dilithium_26.vhd",
      "impl\/vhdl\/pqcrystals_dilithium_27.vhd",
      "impl\/vhdl\/pqcrystals_dilithium_28.vhd",
      "impl\/vhdl\/pqcrystals_dilithium_29.vhd",
      "impl\/vhdl\/pqcrystals_dilithium_30.vhd",
      "impl\/vhdl\/pqcrystals_dilithlbW.vhd",
      "impl\/vhdl\/pqcrystals_dilithocq.vhd",
      "impl\/vhdl\/pqcrystals_dilithtde.vhd",
      "impl\/vhdl\/pqcrystals_dilithudo.vhd",
      "impl\/vhdl\/pqcrystals_dilithvdy.vhd",
      "impl\/vhdl\/pqcrystals_dilithwdI.vhd",
      "impl\/vhdl\/rej_uniform.vhd",
      "impl\/vhdl\/crypto_sign.vhd"
    ],
    "Verilog": [
      "impl\/verilog\/crypto_sign_mac_mhbi.v",
      "impl\/verilog\/crypto_sign_mac_mjbC.v",
      "impl\/verilog\/crypto_sign_mac_mkbM.v",
      "impl\/verilog\/crypto_sign_urem_dEe.v",
      "impl\/verilog\/keccak_absorb.v",
      "impl\/verilog\/keccak_absorb_2.v",
      "impl\/verilog\/keccak_absorb_2_t.v",
      "impl\/verilog\/keccak_absorb_3199.v",
      "impl\/verilog\/keccak_squeezeblocks.v",
      "impl\/verilog\/keccak_squeezeblocks_1.v",
      "impl\/verilog\/keccak_squeezeblocks_2.v",
      "impl\/verilog\/KeccakF1600_StatePer.v",
      "impl\/verilog\/KeccakF1600_StatePer_1.v",
      "impl\/verilog\/pqcrystals_dilithbkb.v",
      "impl\/verilog\/pqcrystals_dilithcud.v",
      "impl\/verilog\/pqcrystals_dilitheOg.v",
      "impl\/verilog\/pqcrystals_dilitheOg_rom.dat",
      "impl\/verilog\/pqcrystals_dilithfYi.v",
      "impl\/verilog\/pqcrystals_dilithium.v",
      "impl\/verilog\/pqcrystals_dilithium_1.v",
      "impl\/verilog\/pqcrystals_dilithium_2.v",
      "impl\/verilog\/pqcrystals_dilithium_3.v",
      "impl\/verilog\/pqcrystals_dilithium_4.v",
      "impl\/verilog\/pqcrystals_dilithium_5.v",
      "impl\/verilog\/pqcrystals_dilithium_6.v",
      "impl\/verilog\/pqcrystals_dilithium_7.v",
      "impl\/verilog\/pqcrystals_dilithium_8.v",
      "impl\/verilog\/pqcrystals_dilithium_9.v",
      "impl\/verilog\/pqcrystals_dilithium_10.v",
      "impl\/verilog\/pqcrystals_dilithium_11.v",
      "impl\/verilog\/pqcrystals_dilithium_12.v",
      "impl\/verilog\/pqcrystals_dilithium_13.v",
      "impl\/verilog\/pqcrystals_dilithium_14.v",
      "impl\/verilog\/pqcrystals_dilithium_15.v",
      "impl\/verilog\/pqcrystals_dilithium_16.v",
      "impl\/verilog\/pqcrystals_dilithium_17.v",
      "impl\/verilog\/pqcrystals_dilithium_18.v",
      "impl\/verilog\/pqcrystals_dilithium_19.v",
      "impl\/verilog\/pqcrystals_dilithium_20.v",
      "impl\/verilog\/pqcrystals_dilithium_21.v",
      "impl\/verilog\/pqcrystals_dilithium_22.v",
      "impl\/verilog\/pqcrystals_dilithium_23.v",
      "impl\/verilog\/pqcrystals_dilithium_24.v",
      "impl\/verilog\/pqcrystals_dilithium_25.v",
      "impl\/verilog\/pqcrystals_dilithium_26.v",
      "impl\/verilog\/pqcrystals_dilithium_27.v",
      "impl\/verilog\/pqcrystals_dilithium_28.v",
      "impl\/verilog\/pqcrystals_dilithium_29.v",
      "impl\/verilog\/pqcrystals_dilithium_30.v",
      "impl\/verilog\/pqcrystals_dilithlbW.v",
      "impl\/verilog\/pqcrystals_dilithocq.v",
      "impl\/verilog\/pqcrystals_dilithtde.v",
      "impl\/verilog\/pqcrystals_dilithudo.v",
      "impl\/verilog\/pqcrystals_dilithvdy.v",
      "impl\/verilog\/pqcrystals_dilithwdI.v",
      "impl\/verilog\/rej_uniform.v",
      "impl\/verilog\/crypto_sign.v"
    ],
    "Misc": ["impl\/misc\/logo.png"],
    "DesignXml": "\/home\/cse\/Downloads\/time\/dilithium2\/crypto_sign\/solution1\/.autopilot\/db\/crypto_sign.design.xml",
    "DebugDir": "\/home\/cse\/Downloads\/time\/dilithium2\/crypto_sign\/solution1\/.debug",
    "ProtoInst": ["\/home\/cse\/Downloads\/time\/dilithium2\/crypto_sign\/solution1\/.debug\/crypto_sign.protoinst"]
  },
  "SubcoreInfo": {
    "HasXpmMemory": false,
    "HasClockedDsp": false,
    "IP": []
  },
  "Interfaces": {
    "ap_clk": {
      "type": "clock",
      "ctype": {"CLK": {"Type": "bool"}},
      "bundle_name": "ap_clk",
      "bundle_role": "default",
      "reset": "ap_rst"
    },
    "ap_ctrl": {
      "type": "ap_ctrl",
      "ctrl_ports": "ap_start ap_done ap_idle ap_ready",
      "ctype": {
        "start": {"Type": "bool"},
        "done": {"Type": "bool"},
        "idle": {"Type": "bool"},
        "ready": {"Type": "bool"}
      }
    },
    "ap_return": {
      "type": "data",
      "dir": "out",
      "width": "32",
      "ctype": {"DATA": {
          "Type": "integer signed",
          "Width": "32"
        }},
      "bundle_name": "ap_return",
      "bundle_role": "default"
    },
    "ap_rst": {
      "type": "reset",
      "polarity": "ACTIVE_HIGH",
      "ctype": {"RST": {"Type": "bool"}},
      "bundle_name": "ap_rst",
      "bundle_role": "default"
    },
    "m_address0": {
      "type": "data",
      "dir": "out",
      "width": "12",
      "ctype": {"DATA": {
          "Type": "null",
          "Width": "12"
        }},
      "bundle_name": "m",
      "bundle_role": "address0"
    },
    "m_q0": {
      "type": "data",
      "dir": "in",
      "width": "8",
      "ctype": {"DATA": {
          "Type": "integer unsigned",
          "Width": "8"
        }},
      "bundle_name": "m",
      "bundle_role": "q0"
    },
    "mlen": {
      "type": "data",
      "dir": "in",
      "width": "64",
      "ctype": {"DATA": {
          "Type": "integer signed",
          "Width": "64"
        }},
      "bundle_name": "mlen",
      "bundle_role": "default"
    },
    "sk_address0": {
      "type": "data",
      "dir": "out",
      "width": "12",
      "ctype": {"DATA": {
          "Type": "null",
          "Width": "12"
        }},
      "bundle_name": "sk",
      "bundle_role": "address0"
    },
    "sk_address1": {
      "type": "data",
      "dir": "out",
      "width": "12",
      "ctype": {"DATA": {
          "Type": "null",
          "Width": "12"
        }},
      "bundle_name": "sk",
      "bundle_role": "address1"
    },
    "sk_q0": {
      "type": "data",
      "dir": "in",
      "width": "8",
      "ctype": {"DATA": {
          "Type": "integer unsigned",
          "Width": "8"
        }},
      "bundle_name": "sk",
      "bundle_role": "q0"
    },
    "sk_q1": {
      "type": "data",
      "dir": "in",
      "width": "8",
      "ctype": {"DATA": {
          "Type": "integer unsigned",
          "Width": "8"
        }},
      "bundle_name": "sk",
      "bundle_role": "q1"
    },
    "sm_address0": {
      "type": "data",
      "dir": "out",
      "width": "13",
      "ctype": {"DATA": {
          "Type": "null",
          "Width": "13"
        }},
      "bundle_name": "sm",
      "bundle_role": "address0"
    },
    "sm_address1": {
      "type": "data",
      "dir": "out",
      "width": "13",
      "ctype": {"DATA": {
          "Type": "null",
          "Width": "13"
        }},
      "bundle_name": "sm",
      "bundle_role": "address1"
    },
    "sm_d0": {
      "type": "data",
      "dir": "out",
      "width": "8",
      "ctype": {"DATA": {
          "Type": "integer unsigned",
          "Width": "8"
        }},
      "bundle_name": "sm",
      "bundle_role": "d0"
    },
    "sm_d1": {
      "type": "data",
      "dir": "out",
      "width": "8",
      "ctype": {"DATA": {
          "Type": "integer unsigned",
          "Width": "8"
        }},
      "bundle_name": "sm",
      "bundle_role": "d1"
    },
    "sm_q0": {
      "type": "data",
      "dir": "in",
      "width": "8",
      "ctype": {"DATA": {
          "Type": "integer unsigned",
          "Width": "8"
        }},
      "bundle_name": "sm",
      "bundle_role": "q0"
    },
    "sm_q1": {
      "type": "data",
      "dir": "in",
      "width": "8",
      "ctype": {"DATA": {
          "Type": "integer unsigned",
          "Width": "8"
        }},
      "bundle_name": "sm",
      "bundle_role": "q1"
    },
    "smlen": {
      "type": "data",
      "dir": "out",
      "width": "64",
      "ctype": {"DATA": {
          "Type": "integer signed",
          "Width": "64"
        }},
      "bundle_name": "smlen",
      "bundle_role": "default"
    }
  },
  "RtlPorts": {
    "ap_clk": {
      "dir": "in",
      "width": "1"
    },
    "ap_rst": {
      "dir": "in",
      "width": "1"
    },
    "ap_start": {
      "dir": "in",
      "width": "1"
    },
    "ap_done": {
      "dir": "out",
      "width": "1"
    },
    "ap_idle": {
      "dir": "out",
      "width": "1"
    },
    "ap_ready": {
      "dir": "out",
      "width": "1"
    },
    "ap_return": {
      "dir": "out",
      "width": "32"
    },
    "sm_address0": {
      "dir": "out",
      "width": "13"
    },
    "sm_ce0": {
      "dir": "out",
      "width": "1"
    },
    "sm_we0": {
      "dir": "out",
      "width": "1"
    },
    "sm_d0": {
      "dir": "out",
      "width": "8"
    },
    "sm_q0": {
      "dir": "in",
      "width": "8"
    },
    "sm_address1": {
      "dir": "out",
      "width": "13"
    },
    "sm_ce1": {
      "dir": "out",
      "width": "1"
    },
    "sm_we1": {
      "dir": "out",
      "width": "1"
    },
    "sm_d1": {
      "dir": "out",
      "width": "8"
    },
    "sm_q1": {
      "dir": "in",
      "width": "8"
    },
    "smlen": {
      "dir": "out",
      "width": "64"
    },
    "smlen_ap_vld": {
      "dir": "out",
      "width": "1"
    },
    "m_address0": {
      "dir": "out",
      "width": "12"
    },
    "m_ce0": {
      "dir": "out",
      "width": "1"
    },
    "m_q0": {
      "dir": "in",
      "width": "8"
    },
    "mlen": {
      "dir": "in",
      "width": "64"
    },
    "sk_address0": {
      "dir": "out",
      "width": "12"
    },
    "sk_ce0": {
      "dir": "out",
      "width": "1"
    },
    "sk_q0": {
      "dir": "in",
      "width": "8"
    },
    "sk_address1": {
      "dir": "out",
      "width": "12"
    },
    "sk_ce1": {
      "dir": "out",
      "width": "1"
    },
    "sk_q1": {
      "dir": "in",
      "width": "8"
    }
  },
  "ModuleInfo": {
    "Hierarchy": {
      "ModuleName": "crypto_sign",
      "Instances": [{
          "ModuleName": "pqcrystals_dilithium_1",
          "InstanceName": "grp_pqcrystals_dilithium_1_fu_101",
          "Instances": [
            {
              "ModuleName": "pqcrystals_dilithium_9",
              "InstanceName": "grp_pqcrystals_dilithium_9_fu_1287",
              "Instances": [
                {
                  "ModuleName": "keccak_absorb",
                  "InstanceName": "grp_keccak_absorb_fu_461",
                  "Instances": [{
                      "ModuleName": "KeccakF1600_StatePer_1",
                      "InstanceName": "grp_KeccakF1600_StatePer_1_fu_504"
                    }]
                },
                {
                  "ModuleName": "keccak_squeezeblocks_1",
                  "InstanceName": "grp_keccak_squeezeblocks_1_fu_472",
                  "Instances": [{
                      "ModuleName": "KeccakF1600_StatePer_1",
                      "InstanceName": "grp_KeccakF1600_StatePer_1_fu_197"
                    }]
                },
                {
                  "ModuleName": "pqcrystals_dilithium_3",
                  "InstanceName": "grp_pqcrystals_dilithium_3_fu_478"
                }
              ]
            },
            {
              "ModuleName": "pqcrystals_dilithium_19",
              "InstanceName": "grp_pqcrystals_dilithium_19_fu_1299",
              "Instances": [
                {
                  "ModuleName": "keccak_absorb_2",
                  "InstanceName": "grp_keccak_absorb_2_fu_4697",
                  "Instances": [{
                      "ModuleName": "KeccakF1600_StatePer_1",
                      "InstanceName": "grp_KeccakF1600_StatePer_1_fu_758"
                    }]
                },
                {
                  "ModuleName": "keccak_squeezeblocks",
                  "InstanceName": "grp_keccak_squeezeblocks_fu_4710",
                  "Instances": [{
                      "ModuleName": "KeccakF1600_StatePer_1",
                      "InstanceName": "grp_KeccakF1600_StatePer_1_fu_198"
                    }]
                }
              ]
            },
            {
              "ModuleName": "pqcrystals_dilithium_10",
              "InstanceName": "grp_pqcrystals_dilithium_10_fu_1306",
              "Instances": [
                {
                  "ModuleName": "keccak_absorb",
                  "InstanceName": "grp_keccak_absorb_fu_547",
                  "Instances": [{
                      "ModuleName": "KeccakF1600_StatePer_1",
                      "InstanceName": "grp_KeccakF1600_StatePer_1_fu_504"
                    }]
                },
                {
                  "ModuleName": "keccak_squeezeblocks_2",
                  "InstanceName": "grp_keccak_squeezeblocks_2_fu_558",
                  "Instances": [{
                      "ModuleName": "KeccakF1600_StatePer_1",
                      "InstanceName": "grp_KeccakF1600_StatePer_1_fu_217"
                    }]
                },
                {
                  "ModuleName": "rej_uniform",
                  "InstanceName": "grp_rej_uniform_fu_569"
                }
              ]
            },
            {
              "ModuleName": "keccak_absorb_2",
              "InstanceName": "grp_keccak_absorb_2_fu_1339",
              "Instances": [{
                  "ModuleName": "KeccakF1600_StatePer_1",
                  "InstanceName": "grp_KeccakF1600_StatePer_1_fu_758"
                }]
            },
            {
              "ModuleName": "KeccakF1600_StatePer_1",
              "InstanceName": "grp_KeccakF1600_StatePer_1_fu_1354"
            },
            {
              "ModuleName": "KeccakF1600_StatePer",
              "InstanceName": "grp_KeccakF1600_StatePer_fu_1359"
            },
            {
              "ModuleName": "pqcrystals_dilithium_23",
              "InstanceName": "grp_pqcrystals_dilithium_23_fu_1364",
              "Instances": [{
                  "ModuleName": "pqcrystals_dilithium_4",
                  "InstanceName": "grp_pqcrystals_dilithium_4_fu_31697"
                }]
            },
            {
              "ModuleName": "pqcrystals_dilithium_25",
              "InstanceName": "grp_pqcrystals_dilithium_25_fu_1372",
              "Instances": [
                {
                  "ModuleName": "pqcrystals_dilithium_26",
                  "InstanceName": "grp_pqcrystals_dilithium_26_fu_2922"
                },
                {
                  "ModuleName": "pqcrystals_dilithium_26",
                  "InstanceName": "grp_pqcrystals_dilithium_26_fu_2927"
                },
                {
                  "ModuleName": "pqcrystals_dilithium_26",
                  "InstanceName": "grp_pqcrystals_dilithium_26_fu_2932"
                }
              ]
            },
            {
              "ModuleName": "pqcrystals_dilithium_25",
              "InstanceName": "grp_pqcrystals_dilithium_25_fu_1381",
              "Instances": [
                {
                  "ModuleName": "pqcrystals_dilithium_26",
                  "InstanceName": "grp_pqcrystals_dilithium_26_fu_2922"
                },
                {
                  "ModuleName": "pqcrystals_dilithium_26",
                  "InstanceName": "grp_pqcrystals_dilithium_26_fu_2927"
                },
                {
                  "ModuleName": "pqcrystals_dilithium_26",
                  "InstanceName": "grp_pqcrystals_dilithium_26_fu_2932"
                }
              ]
            },
            {
              "ModuleName": "pqcrystals_dilithium_25",
              "InstanceName": "grp_pqcrystals_dilithium_25_fu_1390",
              "Instances": [
                {
                  "ModuleName": "pqcrystals_dilithium_26",
                  "InstanceName": "grp_pqcrystals_dilithium_26_fu_2922"
                },
                {
                  "ModuleName": "pqcrystals_dilithium_26",
                  "InstanceName": "grp_pqcrystals_dilithium_26_fu_2927"
                },
                {
                  "ModuleName": "pqcrystals_dilithium_26",
                  "InstanceName": "grp_pqcrystals_dilithium_26_fu_2932"
                }
              ]
            },
            {
              "ModuleName": "pqcrystals_dilithium_24",
              "InstanceName": "grp_pqcrystals_dilithium_24_fu_1408",
              "Instances": [
                {
                  "ModuleName": "pqcrystals_dilithium_26",
                  "InstanceName": "grp_pqcrystals_dilithium_26_fu_3160"
                },
                {
                  "ModuleName": "pqcrystals_dilithium_26",
                  "InstanceName": "grp_pqcrystals_dilithium_26_fu_3165"
                },
                {
                  "ModuleName": "pqcrystals_dilithium_26",
                  "InstanceName": "grp_pqcrystals_dilithium_26_fu_3170"
                },
                {
                  "ModuleName": "pqcrystals_dilithium_26",
                  "InstanceName": "t_3_0_10_pqcrystals_dilithium_26_fu_3175"
                }
              ]
            },
            {
              "ModuleName": "pqcrystals_dilithium",
              "InstanceName": "grp_pqcrystals_dilithium_fu_1415",
              "Instances": [
                {
                  "ModuleName": "pqcrystals_dilithium_7",
                  "InstanceName": "grp_pqcrystals_dilithium_7_fu_2306"
                },
                {
                  "ModuleName": "pqcrystals_dilithium_8",
                  "InstanceName": "grp_pqcrystals_dilithium_8_fu_2324"
                }
              ]
            },
            {
              "ModuleName": "pqcrystals_dilithium_17",
              "InstanceName": "grp_pqcrystals_dilithium_17_fu_1425",
              "Instances": [
                {
                  "ModuleName": "pqcrystals_dilithium_29",
                  "InstanceName": "grp_pqcrystals_dilithium_29_fu_4650"
                },
                {
                  "ModuleName": "pqcrystals_dilithium_29",
                  "InstanceName": "grp_pqcrystals_dilithium_29_fu_4656"
                }
              ]
            },
            {
              "ModuleName": "pqcrystals_dilithium_22",
              "InstanceName": "grp_pqcrystals_dilithium_22_fu_1433"
            },
            {
              "ModuleName": "pqcrystals_dilithium_11",
              "InstanceName": "grp_pqcrystals_dilithium_11_fu_1454"
            },
            {
              "ModuleName": "pqcrystals_dilithium_18",
              "InstanceName": "grp_pqcrystals_dilithium_18_fu_1475"
            },
            {
              "ModuleName": "pqcrystals_dilithium_21",
              "InstanceName": "grp_pqcrystals_dilithium_21_fu_1487"
            },
            {
              "ModuleName": "pqcrystals_dilithium_6",
              "InstanceName": "grp_pqcrystals_dilithium_6_fu_1498",
              "Instances": [{
                  "ModuleName": "pqcrystals_dilithium_18",
                  "InstanceName": "grp_pqcrystals_dilithium_18_fu_35"
                }]
            },
            {
              "ModuleName": "pqcrystals_dilithium_28",
              "InstanceName": "grp_pqcrystals_dilithium_28_fu_1506",
              "Instances": [
                {
                  "ModuleName": "pqcrystals_dilithium_26",
                  "InstanceName": "grp_pqcrystals_dilithium_26_fu_2922"
                },
                {
                  "ModuleName": "pqcrystals_dilithium_26",
                  "InstanceName": "grp_pqcrystals_dilithium_26_fu_2929"
                }
              ]
            },
            {
              "ModuleName": "pqcrystals_dilithium_14",
              "InstanceName": "grp_pqcrystals_dilithium_14_fu_1518",
              "Instances": [
                {
                  "ModuleName": "pqcrystals_dilithium_26",
                  "InstanceName": "grp_pqcrystals_dilithium_26_fu_8001"
                },
                {
                  "ModuleName": "pqcrystals_dilithium_26",
                  "InstanceName": "grp_pqcrystals_dilithium_26_fu_8007"
                }
              ]
            },
            {
              "ModuleName": "pqcrystals_dilithium_15",
              "InstanceName": "grp_pqcrystals_dilithium_15_fu_1535",
              "Instances": [
                {
                  "ModuleName": "pqcrystals_dilithium_26",
                  "InstanceName": "grp_pqcrystals_dilithium_26_fu_8009"
                },
                {
                  "ModuleName": "pqcrystals_dilithium_26",
                  "InstanceName": "grp_pqcrystals_dilithium_26_fu_8015"
                }
              ]
            },
            {
              "ModuleName": "pqcrystals_dilithium_13",
              "InstanceName": "grp_pqcrystals_dilithium_13_fu_1555",
              "Instances": [
                {
                  "ModuleName": "pqcrystals_dilithium_26",
                  "InstanceName": "grp_pqcrystals_dilithium_26_fu_7483"
                },
                {
                  "ModuleName": "pqcrystals_dilithium_26",
                  "InstanceName": "grp_pqcrystals_dilithium_26_fu_7489"
                }
              ]
            },
            {
              "ModuleName": "pqcrystals_dilithium_16",
              "InstanceName": "grp_pqcrystals_dilithium_16_fu_1572",
              "Instances": [
                {
                  "ModuleName": "pqcrystals_dilithium_27",
                  "InstanceName": "grp_pqcrystals_dilithium_27_fu_6725"
                },
                {
                  "ModuleName": "pqcrystals_dilithium_27",
                  "InstanceName": "grp_pqcrystals_dilithium_27_fu_6733"
                }
              ]
            },
            {
              "ModuleName": "pqcrystals_dilithium_20",
              "InstanceName": "grp_pqcrystals_dilithium_20_fu_1594",
              "Instances": [
                {
                  "ModuleName": "pqcrystals_dilithium_30",
                  "InstanceName": "grp_pqcrystals_dilithium_30_fu_2591"
                },
                {
                  "ModuleName": "pqcrystals_dilithium_30",
                  "InstanceName": "grp_pqcrystals_dilithium_30_fu_2597"
                }
              ]
            },
            {
              "ModuleName": "pqcrystals_dilithium_12",
              "InstanceName": "grp_pqcrystals_dilithium_12_fu_1604",
              "Instances": [
                {
                  "ModuleName": "pqcrystals_dilithium_2",
                  "InstanceName": "grp_pqcrystals_dilithium_2_fu_2591"
                },
                {
                  "ModuleName": "pqcrystals_dilithium_2",
                  "InstanceName": "grp_pqcrystals_dilithium_2_fu_2597"
                }
              ]
            },
            {
              "ModuleName": "pqcrystals_dilithium_5",
              "InstanceName": "grp_pqcrystals_dilithium_5_fu_1614"
            },
            {
              "ModuleName": "keccak_absorb_3199",
              "InstanceName": "grp_keccak_absorb_3199_fu_1631"
            }
          ]
        }]
    },
    "Info": {
      "pqcrystals_dilithium_8": {
        "FunctionProtocol": "ap_ctrl_hs",
        "isTaskLevelControl": "1",
        "isPipelined": "0",
        "isCombinational": "0",
        "isOneStateSeq": "0"
      },
      "pqcrystals_dilithium_7": {
        "FunctionProtocol": "ap_ctrl_hs",
        "isTaskLevelControl": "1",
        "isPipelined": "0",
        "isCombinational": "0",
        "isOneStateSeq": "0"
      },
      "pqcrystals_dilithium": {
        "FunctionProtocol": "ap_ctrl_hs",
        "isTaskLevelControl": "1",
        "isPipelined": "0",
        "isCombinational": "0",
        "isOneStateSeq": "0"
      },
      "keccak_absorb_3199": {
        "FunctionProtocol": "ap_ctrl_hs",
        "isTaskLevelControl": "1",
        "isPipelined": "0",
        "isCombinational": "0",
        "isOneStateSeq": "0"
      },
      "KeccakF1600_StatePer_1": {
        "FunctionProtocol": "ap_ctrl_hs",
        "isTaskLevelControl": "1",
        "isPipelined": "0",
        "isCombinational": "0",
        "isOneStateSeq": "0"
      },
      "keccak_absorb_2": {
        "FunctionProtocol": "ap_ctrl_hs",
        "isTaskLevelControl": "1",
        "isPipelined": "0",
        "isCombinational": "0",
        "isOneStateSeq": "0"
      },
      "KeccakF1600_StatePer": {
        "FunctionProtocol": "ap_ctrl_hs",
        "isTaskLevelControl": "1",
        "isPipelined": "0",
        "isCombinational": "0",
        "isOneStateSeq": "0"
      },
      "keccak_absorb": {
        "FunctionProtocol": "ap_ctrl_hs",
        "isTaskLevelControl": "1",
        "isPipelined": "0",
        "isCombinational": "0",
        "isOneStateSeq": "0"
      },
      "keccak_squeezeblocks_2": {
        "FunctionProtocol": "ap_ctrl_hs",
        "isTaskLevelControl": "1",
        "isPipelined": "0",
        "isCombinational": "0",
        "isOneStateSeq": "0"
      },
      "rej_uniform": {
        "FunctionProtocol": "ap_ctrl_hs",
        "isTaskLevelControl": "1",
        "isPipelined": "0",
        "isCombinational": "0",
        "isOneStateSeq": "0"
      },
      "pqcrystals_dilithium_10": {
        "FunctionProtocol": "ap_ctrl_hs",
        "isTaskLevelControl": "1",
        "isPipelined": "0",
        "isCombinational": "0",
        "isOneStateSeq": "0"
      },
      "pqcrystals_dilithium_26": {
        "FunctionProtocol": "ap_ctrl_hs",
        "isTaskLevelControl": "1",
        "isPipelined": "0",
        "isCombinational": "1",
        "isOneStateSeq": "0"
      },
      "pqcrystals_dilithium_25": {
        "FunctionProtocol": "ap_ctrl_hs",
        "isTaskLevelControl": "1",
        "isPipelined": "0",
        "isCombinational": "0",
        "isOneStateSeq": "0"
      },
      "keccak_squeezeblocks_1": {
        "FunctionProtocol": "ap_ctrl_hs",
        "isTaskLevelControl": "1",
        "isPipelined": "0",
        "isCombinational": "0",
        "isOneStateSeq": "0"
      },
      "pqcrystals_dilithium_3": {
        "FunctionProtocol": "ap_ctrl_hs",
        "isTaskLevelControl": "1",
        "isPipelined": "0",
        "isCombinational": "0",
        "isOneStateSeq": "0"
      },
      "pqcrystals_dilithium_9": {
        "FunctionProtocol": "ap_ctrl_hs",
        "isTaskLevelControl": "1",
        "isPipelined": "0",
        "isCombinational": "0",
        "isOneStateSeq": "0"
      },
      "pqcrystals_dilithium_14": {
        "FunctionProtocol": "ap_ctrl_hs",
        "isTaskLevelControl": "1",
        "isPipelined": "0",
        "isCombinational": "0",
        "isOneStateSeq": "0"
      },
      "pqcrystals_dilithium_15": {
        "FunctionProtocol": "ap_ctrl_hs",
        "isTaskLevelControl": "1",
        "isPipelined": "0",
        "isCombinational": "0",
        "isOneStateSeq": "0"
      },
      "pqcrystals_dilithium_21": {
        "FunctionProtocol": "ap_ctrl_hs",
        "isTaskLevelControl": "1",
        "isPipelined": "0",
        "isCombinational": "0",
        "isOneStateSeq": "0"
      },
      "pqcrystals_dilithium_2": {
        "FunctionProtocol": "ap_ctrl_hs",
        "isTaskLevelControl": "1",
        "isPipelined": "0",
        "isCombinational": "1",
        "isOneStateSeq": "0"
      },
      "pqcrystals_dilithium_12": {
        "FunctionProtocol": "ap_ctrl_hs",
        "isTaskLevelControl": "1",
        "isPipelined": "0",
        "isCombinational": "0",
        "isOneStateSeq": "0"
      },
      "pqcrystals_dilithium_28": {
        "FunctionProtocol": "ap_ctrl_hs",
        "isTaskLevelControl": "1",
        "isPipelined": "0",
        "isCombinational": "0",
        "isOneStateSeq": "0"
      },
      "pqcrystals_dilithium_30": {
        "FunctionProtocol": "ap_ctrl_hs",
        "isTaskLevelControl": "1",
        "isPipelined": "0",
        "isCombinational": "1",
        "isOneStateSeq": "0"
      },
      "pqcrystals_dilithium_20": {
        "FunctionProtocol": "ap_ctrl_hs",
        "isTaskLevelControl": "1",
        "isPipelined": "0",
        "isCombinational": "0",
        "isOneStateSeq": "0"
      },
      "pqcrystals_dilithium_29": {
        "FunctionProtocol": "ap_ctrl_hs",
        "isTaskLevelControl": "1",
        "isPipelined": "0",
        "isCombinational": "1",
        "isOneStateSeq": "0"
      },
      "pqcrystals_dilithium_17": {
        "FunctionProtocol": "ap_ctrl_hs",
        "isTaskLevelControl": "1",
        "isPipelined": "0",
        "isCombinational": "0",
        "isOneStateSeq": "0"
      },
      "pqcrystals_dilithium_5": {
        "FunctionProtocol": "ap_ctrl_hs",
        "isTaskLevelControl": "1",
        "isPipelined": "0",
        "isCombinational": "0",
        "isOneStateSeq": "0"
      },
      "keccak_squeezeblocks": {
        "FunctionProtocol": "ap_ctrl_hs",
        "isTaskLevelControl": "1",
        "isPipelined": "0",
        "isCombinational": "0",
        "isOneStateSeq": "0"
      },
      "pqcrystals_dilithium_19": {
        "FunctionProtocol": "ap_ctrl_hs",
        "isTaskLevelControl": "1",
        "isPipelined": "0",
        "isCombinational": "0",
        "isOneStateSeq": "0"
      },
      "pqcrystals_dilithium_24": {
        "FunctionProtocol": "ap_ctrl_hs",
        "isTaskLevelControl": "1",
        "isPipelined": "0",
        "isCombinational": "0",
        "isOneStateSeq": "0"
      },
      "pqcrystals_dilithium_13": {
        "FunctionProtocol": "ap_ctrl_hs",
        "isTaskLevelControl": "1",
        "isPipelined": "0",
        "isCombinational": "0",
        "isOneStateSeq": "0"
      },
      "pqcrystals_dilithium_22": {
        "FunctionProtocol": "ap_ctrl_hs",
        "isTaskLevelControl": "1",
        "isPipelined": "0",
        "isCombinational": "0",
        "isOneStateSeq": "0"
      },
      "pqcrystals_dilithium_18": {
        "FunctionProtocol": "ap_ctrl_hs",
        "isTaskLevelControl": "1",
        "isPipelined": "0",
        "isCombinational": "0",
        "isOneStateSeq": "0"
      },
      "pqcrystals_dilithium_11": {
        "FunctionProtocol": "ap_ctrl_hs",
        "isTaskLevelControl": "1",
        "isPipelined": "0",
        "isCombinational": "0",
        "isOneStateSeq": "0"
      },
      "pqcrystals_dilithium_6": {
        "FunctionProtocol": "ap_ctrl_hs",
        "isTaskLevelControl": "1",
        "isPipelined": "0",
        "isCombinational": "0",
        "isOneStateSeq": "0"
      },
      "pqcrystals_dilithium_27": {
        "FunctionProtocol": "ap_ctrl_hs",
        "isTaskLevelControl": "1",
        "isPipelined": "0",
        "isCombinational": "1",
        "isOneStateSeq": "0"
      },
      "pqcrystals_dilithium_16": {
        "FunctionProtocol": "ap_ctrl_hs",
        "isTaskLevelControl": "1",
        "isPipelined": "0",
        "isCombinational": "0",
        "isOneStateSeq": "0"
      },
      "pqcrystals_dilithium_4": {
        "FunctionProtocol": "ap_ctrl_hs",
        "isTaskLevelControl": "1",
        "isPipelined": "0",
        "isCombinational": "0",
        "isOneStateSeq": "0"
      },
      "pqcrystals_dilithium_23": {
        "FunctionProtocol": "ap_ctrl_hs",
        "isTaskLevelControl": "1",
        "isPipelined": "0",
        "isCombinational": "0",
        "isOneStateSeq": "0"
      },
      "pqcrystals_dilithium_1": {
        "FunctionProtocol": "ap_ctrl_hs",
        "isTaskLevelControl": "1",
        "isPipelined": "0",
        "isCombinational": "0",
        "isOneStateSeq": "0"
      },
      "crypto_sign": {
        "FunctionProtocol": "ap_ctrl_hs",
        "isTaskLevelControl": "1",
        "isPipelined": "0",
        "isCombinational": "0",
        "isOneStateSeq": "0"
      }
    },
    "Metrics": {
      "pqcrystals_dilithium_8": {
        "Latency": {
          "LatencyBest": "128",
          "LatencyAvg": "128",
          "LatencyWorst": "128",
          "PipelineII": "128",
          "PipelineDepth": "",
          "PipelineType": "none"
        },
        "Timing": {
          "Target": "10000.00",
          "Uncertainty": "1250.00",
          "Estimate": "6.890"
        },
        "Area": {
          "FF": "194",
          "LUT": "11329",
          "BRAM_18K": "0",
          "DSP48E": "0",
          "URAM": "0"
        }
      },
      "pqcrystals_dilithium_7": {
        "Latency": {
          "LatencyBest": "208",
          "LatencyAvg": "208",
          "LatencyWorst": "208",
          "PipelineII": "208",
          "PipelineDepth": "",
          "PipelineType": "none"
        },
        "Timing": {
          "Target": "10000.00",
          "Uncertainty": "1250.00",
          "Estimate": "7.354"
        },
        "Area": {
          "FF": "259",
          "LUT": "22705",
          "BRAM_18K": "0",
          "DSP48E": "0",
          "URAM": "0"
        }
      },
      "pqcrystals_dilithium": {
        "Latency": {
          "LatencyBest": "1936",
          "LatencyAvg": "1936",
          "LatencyWorst": "1936",
          "PipelineII": "1936",
          "PipelineDepth": "",
          "PipelineType": "none"
        },
        "Timing": {
          "Target": "10000.00",
          "Uncertainty": "1250.00",
          "Estimate": "7.354"
        },
        "Area": {
          "FF": "536",
          "LUT": "35666",
          "BRAM_18K": "0",
          "DSP48E": "0",
          "URAM": "0"
        }
      },
      "keccak_absorb_3199": {
        "Latency": {
          "LatencyBest": "26",
          "LatencyAvg": "26",
          "LatencyWorst": "26",
          "PipelineII": "26",
          "PipelineDepth": "",
          "PipelineType": "none"
        },
        "Timing": {
          "Target": "10000.00",
          "Uncertainty": "1250.00",
          "Estimate": "6.352"
        },
        "Loops": [{
            "Name": "Loop 1",
            "TripCount": "6",
            "Latency": "24",
            "PipelineII": "4",
            "PipelineDepth": "5"
          }],
        "Area": {
          "FF": "138",
          "LUT": "326",
          "BRAM_18K": "0",
          "DSP48E": "0",
          "URAM": "0"
        }
      },
      "KeccakF1600_StatePer_1": {
        "Latency": {
          "LatencyBest": "25",
          "LatencyAvg": "25",
          "LatencyWorst": "25",
          "PipelineII": "25",
          "PipelineDepth": "",
          "PipelineType": "none"
        },
        "Timing": {
          "Target": "10000.00",
          "Uncertainty": "1250.00",
          "Estimate": "83.112"
        },
        "Area": {
          "FF": "3866",
          "LUT": "194018",
          "BRAM_18K": "0",
          "DSP48E": "0",
          "URAM": "0"
        }
      },
      "keccak_absorb_2": {
        "Latency": {
          "LatencyBest": "",
          "LatencyAvg": "",
          "LatencyWorst": "",
          "PipelineII": "",
          "PipelineDepth": "",
          "PipelineType": "none"
        },
        "Timing": {
          "Target": "10000.00",
          "Uncertainty": "1250.00",
          "Estimate": "83.112"
        },
        "Loops": [
          {
            "Name": "memset_t",
            "TripCount": "8",
            "Latency": "7",
            "PipelineII": "",
            "PipelineDepth": "1"
          },
          {
            "Name": "Loop 2",
            "TripCount": "",
            "Latency": "",
            "PipelineII": "",
            "PipelineDepth": "2"
          },
          {
            "Name": "Loop 3",
            "TripCount": "",
            "Latency": "",
            "PipelineII": "4",
            "PipelineDepth": "5"
          },
          {
            "Name": "Loop 4",
            "TripCount": "",
            "Latency": "",
            "PipelineII": "",
            "PipelineDepth": "113",
            "Loops": [{
                "Name": "Loop 4.1",
                "TripCount": "17",
                "Latency": "85",
                "PipelineII": "",
                "PipelineDepth": "5"
              }]
          },
          {
            "Name": "Loop 5",
            "TripCount": "",
            "LatencyMin": "0",
            "LatencyMax": "64",
            "Latency": "0 ~ 64",
            "PipelineII": "4",
            "PipelineDepth": "5"
          },
          {
            "Name": "Loop 6",
            "TripCount": "",
            "Latency": "",
            "PipelineII": "1",
            "PipelineDepth": "2"
          }
        ],
        "Area": {
          "BRAM_18K": "1",
          "FF": "5537",
          "LUT": "197422",
          "URAM": "0",
          "DSP48E": "0"
        }
      },
      "KeccakF1600_StatePer": {
        "Latency": {
          "LatencyBest": "25",
          "LatencyAvg": "25",
          "LatencyWorst": "25",
          "PipelineII": "25",
          "PipelineDepth": "",
          "PipelineType": "none"
        },
        "Timing": {
          "Target": "10000.00",
          "Uncertainty": "1250.00",
          "Estimate": "83.112"
        },
        "Area": {
          "FF": "3866",
          "LUT": "194018",
          "BRAM_18K": "0",
          "DSP48E": "0",
          "URAM": "0"
        }
      },
      "keccak_absorb": {
        "Latency": {
          "LatencyBest": "",
          "LatencyAvg": "",
          "LatencyWorst": "",
          "PipelineII": "",
          "PipelineDepth": "",
          "PipelineType": "none"
        },
        "Timing": {
          "Target": "10000.00",
          "Uncertainty": "1250.00",
          "Estimate": "83.112"
        },
        "Loops": [
          {
            "Name": "memset_t",
            "TripCount": "8",
            "Latency": "7",
            "PipelineII": "",
            "PipelineDepth": "1"
          },
          {
            "Name": "Loop 2",
            "TripCount": "",
            "Latency": "",
            "PipelineII": "",
            "PipelineDepth": "1"
          },
          {
            "Name": "Loop 3",
            "TripCount": "",
            "Latency": "",
            "PipelineII": "",
            "PipelineDepthMin": "62",
            "PipelineDepthMax": "70",
            "PipelineDepth": "62 ~ 70",
            "Loops": [{
                "Name": "Loop 3.1",
                "TripCount": "",
                "LatencyMin": "34",
                "LatencyMax": "42",
                "Latency": "34 ~ 42",
                "PipelineII": "",
                "PipelineDepth": "2"
              }]
          },
          {
            "Name": "Loop 4",
            "TripCount": "",
            "LatencyMin": "0",
            "LatencyMax": "40",
            "Latency": "0 ~ 40",
            "PipelineII": "2",
            "PipelineDepth": "2"
          },
          {
            "Name": "Loop 5",
            "TripCount": "",
            "Latency": "",
            "PipelineII": "1",
            "PipelineDepth": "1"
          }
        ],
        "Area": {
          "BRAM_18K": "1",
          "FF": "4767",
          "LUT": "195712",
          "URAM": "0",
          "DSP48E": "0"
        }
      },
      "keccak_squeezeblocks_2": {
        "Latency": {
          "LatencyBest": "134",
          "LatencyAvg": "",
          "LatencyWorst": "666",
          "PipelineIIMin": "134",
          "PipelineIIMax": "666",
          "PipelineII": "134 ~ 666",
          "PipelineDepth": "",
          "PipelineType": "none"
        },
        "Timing": {
          "Target": "10000.00",
          "Uncertainty": "1250.00",
          "Estimate": "83.112"
        },
        "Loops": [{
            "Name": "Loop 1",
            "TripCount": "",
            "LatencyMin": "133",
            "LatencyMax": "665",
            "Latency": "133 ~ 665",
            "PipelineII": "",
            "PipelineDepth": "133",
            "Loops": [{
                "Name": "Loop 1.1",
                "TripCount": "21",
                "Latency": "105",
                "PipelineII": "",
                "PipelineDepth": "5"
              }]
          }],
        "Area": {
          "FF": "3959",
          "LUT": "194470",
          "BRAM_18K": "0",
          "DSP48E": "0",
          "URAM": "0"
        }
      },
      "rej_uniform": {
        "Latency": {
          "LatencyBest": "",
          "LatencyAvg": "",
          "LatencyWorst": "",
          "PipelineII": "",
          "PipelineDepth": "",
          "PipelineType": "none"
        },
        "Timing": {
          "Target": "10000.00",
          "Uncertainty": "1250.00",
          "Estimate": "6.286"
        },
        "Loops": [{
            "Name": "Loop 1",
            "TripCount": "",
            "Latency": "",
            "PipelineII": "",
            "PipelineDepth": "3"
          }],
        "Area": {
          "FF": "174",
          "LUT": "306",
          "BRAM_18K": "0",
          "DSP48E": "0",
          "URAM": "0"
        }
      },
      "pqcrystals_dilithium_10": {
        "Latency": {
          "LatencyBest": "",
          "LatencyAvg": "",
          "LatencyWorst": "",
          "PipelineII": "",
          "PipelineDepth": "",
          "PipelineType": "none"
        },
        "Timing": {
          "Target": "10000.00",
          "Uncertainty": "1250.00",
          "Estimate": "83.112"
        },
        "Loops": [
          {
            "Name": "Loop 1",
            "TripCount": "4",
            "Latency": "16",
            "PipelineII": "4",
            "PipelineDepth": "5"
          },
          {
            "Name": "Loop 2",
            "TripCount": "",
            "Latency": "",
            "PipelineII": "",
            "PipelineDepth": "",
            "Loops": [{
                "Name": "Loop 2.1",
                "TripCount": "",
                "LatencyMin": "0",
                "LatencyMax": "4",
                "Latency": "0 ~ 4",
                "PipelineII": "",
                "PipelineDepth": "2"
              }]
          }
        ],
        "Area": {
          "BRAM_18K": "6",
          "FF": "9337",
          "LUT": "391961",
          "URAM": "0",
          "DSP48E": "0"
        }
      },
      "pqcrystals_dilithium_26": {
        "Latency": {
          "LatencyBest": "0",
          "LatencyAvg": "0",
          "LatencyWorst": "0",
          "PipelineII": "0",
          "PipelineDepth": "",
          "PipelineType": "none"
        },
        "Timing": {
          "Target": "10000.00",
          "Uncertainty": "1250.00",
          "Estimate": "16.758"
        },
        "Area": {
          "DSP48E": "6",
          "FF": "0",
          "LUT": "113",
          "BRAM_18K": "0",
          "URAM": "0"
        }
      },
      "pqcrystals_dilithium_25": {
        "Latency": {
          "LatencyBest": "",
          "LatencyAvg": "",
          "LatencyWorst": "",
          "PipelineII": "",
          "PipelineDepth": "",
          "PipelineType": "none"
        },
        "Timing": {
          "Target": "10000.00",
          "Uncertainty": "1250.00",
          "Estimate": "56.962"
        },
        "Loops": [{
            "Name": "Loop 1",
            "TripCount": "",
            "Latency": "",
            "PipelineII": "",
            "PipelineDepth": "",
            "Loops": [{
                "Name": "Loop 1.1",
                "TripCount": "",
                "Latency": "",
                "PipelineII": "",
                "PipelineDepth": "3"
              }]
          }],
        "Area": {
          "BRAM_18K": "1",
          "DSP48E": "1812",
          "FF": "16512",
          "LUT": "65561",
          "URAM": "0"
        }
      },
      "keccak_squeezeblocks_1": {
        "Latency": {
          "LatencyBest": "566",
          "LatencyAvg": "566",
          "LatencyWorst": "566",
          "PipelineII": "566",
          "PipelineDepth": "",
          "PipelineType": "none"
        },
        "Timing": {
          "Target": "10000.00",
          "Uncertainty": "1250.00",
          "Estimate": "83.112"
        },
        "Loops": [{
            "Name": "Loop 1",
            "TripCount": "5",
            "Latency": "565",
            "PipelineII": "",
            "PipelineDepth": "113",
            "Loops": [{
                "Name": "Loop 1.1",
                "TripCount": "17",
                "Latency": "85",
                "PipelineII": "",
                "PipelineDepth": "5"
              }]
          }],
        "Area": {
          "FF": "3956",
          "LUT": "194405",
          "BRAM_18K": "0",
          "DSP48E": "0",
          "URAM": "0"
        }
      },
      "pqcrystals_dilithium_3": {
        "Latency": {
          "LatencyBest": "288",
          "LatencyAvg": "288",
          "LatencyWorst": "288",
          "PipelineII": "288",
          "PipelineDepth": "",
          "PipelineType": "none"
        },
        "Timing": {
          "Target": "10000.00",
          "Uncertainty": "1250.00",
          "Estimate": "7.448"
        },
        "Area": {
          "FF": "307",
          "LUT": "17772",
          "BRAM_18K": "0",
          "DSP48E": "0",
          "URAM": "0"
        }
      },
      "pqcrystals_dilithium_9": {
        "Latency": {
          "LatencyBest": "",
          "LatencyAvg": "",
          "LatencyWorst": "",
          "PipelineII": "",
          "PipelineDepth": "",
          "PipelineType": "none"
        },
        "Timing": {
          "Target": "10000.00",
          "Uncertainty": "1250.00",
          "Estimate": "83.112"
        },
        "Loops": [{
            "Name": "Loop 1",
            "TripCount": "6",
            "Latency": "24",
            "PipelineII": "4",
            "PipelineDepth": "5"
          }],
        "Area": {
          "BRAM_18K": "6",
          "FF": "9242",
          "LUT": "409020",
          "URAM": "0",
          "DSP48E": "0"
        }
      },
      "pqcrystals_dilithium_14": {
        "Latency": {
          "LatencyBest": "128",
          "LatencyAvg": "128",
          "LatencyWorst": "128",
          "PipelineII": "128",
          "PipelineDepth": "",
          "PipelineType": "none"
        },
        "Timing": {
          "Target": "10000.00",
          "Uncertainty": "1250.00",
          "Estimate": "32.165"
        },
        "Area": {
          "DSP48E": "524",
          "FF": "137",
          "LUT": "17465",
          "BRAM_18K": "0",
          "URAM": "0"
        }
      },
      "pqcrystals_dilithium_15": {
        "Latency": {
          "LatencyBest": "128",
          "LatencyAvg": "128",
          "LatencyWorst": "128",
          "PipelineII": "128",
          "PipelineDepth": "",
          "PipelineType": "none"
        },
        "Timing": {
          "Target": "10000.00",
          "Uncertainty": "1250.00",
          "Estimate": "32.165"
        },
        "Area": {
          "DSP48E": "524",
          "FF": "139",
          "LUT": "17480",
          "BRAM_18K": "0",
          "URAM": "0"
        }
      },
      "pqcrystals_dilithium_21": {
        "Latency": {
          "LatencyBest": "255",
          "LatencyAvg": "255",
          "LatencyWorst": "255",
          "PipelineII": "255",
          "PipelineDepth": "",
          "PipelineType": "none"
        },
        "Timing": {
          "Target": "10000.00",
          "Uncertainty": "1250.00",
          "Estimate": "7.724"
        },
        "Area": {
          "FF": "8900",
          "LUT": "18737",
          "BRAM_18K": "0",
          "DSP48E": "0",
          "URAM": "0"
        }
      },
      "pqcrystals_dilithium_2": {
        "Latency": {
          "LatencyBest": "0",
          "LatencyAvg": "0",
          "LatencyWorst": "0",
          "PipelineII": "0",
          "PipelineDepth": "",
          "PipelineType": "none"
        },
        "Timing": {
          "Target": "10000.00",
          "Uncertainty": "1250.00",
          "Estimate": "8.530"
        },
        "Area": {
          "DSP48E": "1",
          "FF": "0",
          "LUT": "39",
          "BRAM_18K": "0",
          "URAM": "0"
        }
      },
      "pqcrystals_dilithium_12": {
        "Latency": {
          "LatencyBest": "255",
          "LatencyAvg": "255",
          "LatencyWorst": "255",
          "PipelineII": "255",
          "PipelineDepth": "",
          "PipelineType": "none"
        },
        "Timing": {
          "Target": "10000.00",
          "Uncertainty": "1250.00",
          "Estimate": "14.285"
        },
        "Area": {
          "DSP48E": "2",
          "FF": "8900",
          "LUT": "7747",
          "BRAM_18K": "0",
          "URAM": "0"
        }
      },
      "pqcrystals_dilithium_28": {
        "Latency": {
          "LatencyBest": "",
          "LatencyAvg": "",
          "LatencyWorst": "",
          "PipelineII": "",
          "PipelineDepth": "",
          "PipelineType": "none"
        },
        "Timing": {
          "Target": "10000.00",
          "Uncertainty": "1250.00",
          "Estimate": "34.369"
        },
        "Loops": [
          {
            "Name": "Loop 1",
            "TripCount": "",
            "Latency": "",
            "PipelineII": "",
            "PipelineDepth": "",
            "Loops": [{
                "Name": "Loop 1.1",
                "TripCount": "",
                "Latency": "",
                "PipelineII": "",
                "PipelineDepth": "3"
              }]
          },
          {
            "Name": "Loop 2",
            "TripCount": "64",
            "Latency": "",
            "PipelineII": "",
            "PipelineDepth": "",
            "Loops": [{
                "Name": "Loop 2.1",
                "TripCount": "",
                "Latency": "",
                "PipelineII": "",
                "PipelineDepth": "3"
              }]
          },
          {
            "Name": "Loop 3",
            "TripCount": "32",
            "Latency": "",
            "PipelineII": "",
            "PipelineDepth": "",
            "Loops": [{
                "Name": "Loop 3.1",
                "TripCount": "",
                "Latency": "",
                "PipelineII": "",
                "PipelineDepth": "3"
              }]
          },
          {
            "Name": "Loop 4",
            "TripCount": "16",
            "Latency": "",
            "PipelineII": "",
            "PipelineDepth": "",
            "Loops": [{
                "Name": "Loop 4.1",
                "TripCount": "",
                "Latency": "",
                "PipelineII": "",
                "PipelineDepth": "3"
              }]
          },
          {
            "Name": "Loop 5",
            "TripCount": "8",
            "Latency": "",
            "PipelineII": "",
            "PipelineDepth": "",
            "Loops": [{
                "Name": "Loop 5.1",
                "TripCount": "",
                "Latency": "",
                "PipelineII": "",
                "PipelineDepth": "3"
              }]
          },
          {
            "Name": "Loop 6",
            "TripCount": "4",
            "Latency": "",
            "PipelineII": "",
            "PipelineDepth": "",
            "Loops": [{
                "Name": "Loop 6.1",
                "TripCount": "",
                "Latency": "",
                "PipelineII": "",
                "PipelineDepth": "3"
              }]
          },
          {
            "Name": "Loop 7",
            "TripCount": "2",
            "Latency": "",
            "PipelineII": "",
            "PipelineDepth": "",
            "Loops": [{
                "Name": "Loop 7.1",
                "TripCount": "",
                "Latency": "",
                "PipelineII": "",
                "PipelineDepth": "3"
              }]
          },
          {
            "Name": "Loop 8",
            "TripCount": "1",
            "Latency": "",
            "PipelineII": "",
            "PipelineDepth": "",
            "Loops": [{
                "Name": "Loop 8.1",
                "TripCount": "",
                "Latency": "",
                "PipelineII": "",
                "PipelineDepth": "3"
              }]
          }
        ],
        "Area": {
          "BRAM_18K": "1",
          "DSP48E": "540",
          "FF": "10596",
          "LUT": "14867",
          "URAM": "0"
        }
      },
      "pqcrystals_dilithium_30": {
        "Latency": {
          "LatencyBest": "0",
          "LatencyAvg": "0",
          "LatencyWorst": "0",
          "PipelineII": "0",
          "PipelineDepth": "",
          "PipelineType": "none"
        },
        "Timing": {
          "Target": "10000.00",
          "Uncertainty": "1250.00",
          "Estimate": "2.180"
        },
        "Area": {
          "FF": "0",
          "LUT": "62",
          "BRAM_18K": "0",
          "DSP48E": "0",
          "URAM": "0"
        }
      },
      "pqcrystals_dilithium_20": {
        "Latency": {
          "LatencyBest": "255",
          "LatencyAvg": "255",
          "LatencyWorst": "255",
          "PipelineII": "255",
          "PipelineDepth": "",
          "PipelineType": "none"
        },
        "Timing": {
          "Target": "10000.00",
          "Uncertainty": "1250.00",
          "Estimate": "7.935"
        },
        "Area": {
          "FF": "8900",
          "LUT": "7793",
          "BRAM_18K": "0",
          "DSP48E": "0",
          "URAM": "0"
        }
      },
      "pqcrystals_dilithium_29": {
        "Latency": {
          "LatencyBest": "0",
          "LatencyAvg": "0",
          "LatencyWorst": "0",
          "PipelineII": "0",
          "PipelineDepth": "",
          "PipelineType": "none"
        },
        "Timing": {
          "Target": "10000.00",
          "Uncertainty": "1250.00",
          "Estimate": "21.772"
        },
        "Area": {
          "DSP48E": "2",
          "FF": "0",
          "LUT": "168",
          "BRAM_18K": "0",
          "URAM": "0"
        }
      },
      "pqcrystals_dilithium_17": {
        "Latency": {
          "LatencyBest": "255",
          "LatencyAvg": "255",
          "LatencyWorst": "255",
          "PipelineII": "255",
          "PipelineDepth": "",
          "PipelineType": "none"
        },
        "Timing": {
          "Target": "10000.00",
          "Uncertainty": "1250.00",
          "Estimate": "30.299"
        },
        "Area": {
          "DSP48E": "4",
          "FF": "9667",
          "LUT": "8912",
          "BRAM_18K": "0",
          "URAM": "0"
        }
      },
      "pqcrystals_dilithium_5": {
        "Latency": {
          "LatencyBest": "128",
          "LatencyAvg": "128",
          "LatencyWorst": "128",
          "PipelineII": "128",
          "PipelineDepth": "",
          "PipelineType": "none"
        },
        "Timing": {
          "Target": "10000.00",
          "Uncertainty": "1250.00",
          "Estimate": "6.344"
        },
        "Area": {
          "FF": "151",
          "LUT": "11306",
          "BRAM_18K": "0",
          "DSP48E": "0",
          "URAM": "0"
        }
      },
      "keccak_squeezeblocks": {
        "Latency": {
          "LatencyBest": "114",
          "LatencyAvg": "114",
          "LatencyWorst": "114",
          "PipelineII": "114",
          "PipelineDepth": "",
          "PipelineType": "none"
        },
        "Timing": {
          "Target": "10000.00",
          "Uncertainty": "1250.00",
          "Estimate": "83.112"
        },
        "Loops": [{
            "Name": "Loop 1",
            "TripCount": "1",
            "Latency": "113",
            "PipelineII": "",
            "PipelineDepth": "113",
            "Loops": [{
                "Name": "Loop 1.1",
                "TripCount": "17",
                "Latency": "85",
                "PipelineII": "",
                "PipelineDepth": "5"
              }]
          }],
        "Area": {
          "FF": "3950",
          "LUT": "194357",
          "BRAM_18K": "0",
          "DSP48E": "0",
          "URAM": "0"
        }
      },
      "pqcrystals_dilithium_19": {
        "Latency": {
          "LatencyBest": "",
          "LatencyAvg": "",
          "LatencyWorst": "",
          "PipelineII": "",
          "PipelineDepth": "",
          "PipelineType": "none"
        },
        "Timing": {
          "Target": "10000.00",
          "Uncertainty": "1250.00",
          "Estimate": "83.112"
        },
        "Loops": [
          {
            "Name": "Loop 1",
            "TripCount": "",
            "Latency": "",
            "PipelineII": "",
            "PipelineDepthMin": "4",
            "PipelineDepthMax": "118",
            "PipelineDepth": "4 ~ 118"
          },
          {
            "Name": "Loop 2",
            "TripCount": "",
            "Latency": "",
            "PipelineII": "",
            "PipelineDepthMin": "4",
            "PipelineDepthMax": "118",
            "PipelineDepth": "4 ~ 118"
          },
          {
            "Name": "Loop 3",
            "TripCount": "",
            "Latency": "",
            "PipelineII": "",
            "PipelineDepthMin": "4",
            "PipelineDepthMax": "118",
            "PipelineDepth": "4 ~ 118"
          },
          {
            "Name": "Loop 4",
            "TripCount": "",
            "Latency": "",
            "PipelineII": "",
            "PipelineDepthMin": "4",
            "PipelineDepthMax": "118",
            "PipelineDepth": "4 ~ 118"
          },
          {
            "Name": "Loop 5",
            "TripCount": "",
            "Latency": "",
            "PipelineII": "",
            "PipelineDepthMin": "4",
            "PipelineDepthMax": "118",
            "PipelineDepth": "4 ~ 118"
          },
          {
            "Name": "Loop 6",
            "TripCount": "",
            "Latency": "",
            "PipelineII": "",
            "PipelineDepthMin": "4",
            "PipelineDepthMax": "118",
            "PipelineDepth": "4 ~ 118"
          },
          {
            "Name": "Loop 7",
            "TripCount": "",
            "Latency": "",
            "PipelineII": "",
            "PipelineDepthMin": "4",
            "PipelineDepthMax": "118",
            "PipelineDepth": "4 ~ 118"
          },
          {
            "Name": "Loop 8",
            "TripCount": "",
            "Latency": "",
            "PipelineII": "",
            "PipelineDepthMin": "4",
            "PipelineDepthMax": "118",
            "PipelineDepth": "4 ~ 118"
          },
          {
            "Name": "Loop 9",
            "TripCount": "",
            "Latency": "",
            "PipelineII": "",
            "PipelineDepthMin": "4",
            "PipelineDepthMax": "118",
            "PipelineDepth": "4 ~ 118"
          },
          {
            "Name": "Loop 10",
            "TripCount": "",
            "Latency": "",
            "PipelineII": "",
            "PipelineDepthMin": "4",
            "PipelineDepthMax": "118",
            "PipelineDepth": "4 ~ 118"
          },
          {
            "Name": "Loop 11",
            "TripCount": "",
            "Latency": "",
            "PipelineII": "",
            "PipelineDepthMin": "4",
            "PipelineDepthMax": "118",
            "PipelineDepth": "4 ~ 118"
          },
          {
            "Name": "Loop 12",
            "TripCount": "",
            "Latency": "",
            "PipelineII": "",
            "PipelineDepthMin": "4",
            "PipelineDepthMax": "118",
            "PipelineDepth": "4 ~ 118"
          },
          {
            "Name": "Loop 13",
            "TripCount": "",
            "Latency": "",
            "PipelineII": "",
            "PipelineDepthMin": "4",
            "PipelineDepthMax": "118",
            "PipelineDepth": "4 ~ 118"
          },
          {
            "Name": "Loop 14",
            "TripCount": "",
            "Latency": "",
            "PipelineII": "",
            "PipelineDepthMin": "4",
            "PipelineDepthMax": "118",
            "PipelineDepth": "4 ~ 118"
          },
          {
            "Name": "Loop 15",
            "TripCount": "",
            "Latency": "",
            "PipelineII": "",
            "PipelineDepthMin": "4",
            "PipelineDepthMax": "118",
            "PipelineDepth": "4 ~ 118"
          },
          {
            "Name": "Loop 16",
            "TripCount": "",
            "Latency": "",
            "PipelineII": "",
            "PipelineDepthMin": "4",
            "PipelineDepthMax": "118",
            "PipelineDepth": "4 ~ 118"
          },
          {
            "Name": "Loop 17",
            "TripCount": "",
            "Latency": "",
            "PipelineII": "",
            "PipelineDepthMin": "4",
            "PipelineDepthMax": "118",
            "PipelineDepth": "4 ~ 118"
          },
          {
            "Name": "Loop 18",
            "TripCount": "",
            "Latency": "",
            "PipelineII": "",
            "PipelineDepthMin": "4",
            "PipelineDepthMax": "118",
            "PipelineDepth": "4 ~ 118"
          },
          {
            "Name": "Loop 19",
            "TripCount": "",
            "Latency": "",
            "PipelineII": "",
            "PipelineDepthMin": "4",
            "PipelineDepthMax": "118",
            "PipelineDepth": "4 ~ 118"
          },
          {
            "Name": "Loop 20",
            "TripCount": "",
            "Latency": "",
            "PipelineII": "",
            "PipelineDepthMin": "4",
            "PipelineDepthMax": "118",
            "PipelineDepth": "4 ~ 118"
          },
          {
            "Name": "Loop 21",
            "TripCount": "",
            "Latency": "",
            "PipelineII": "",
            "PipelineDepthMin": "4",
            "PipelineDepthMax": "118",
            "PipelineDepth": "4 ~ 118"
          },
          {
            "Name": "Loop 22",
            "TripCount": "",
            "Latency": "",
            "PipelineII": "",
            "PipelineDepthMin": "4",
            "PipelineDepthMax": "118",
            "PipelineDepth": "4 ~ 118"
          },
          {
            "Name": "Loop 23",
            "TripCount": "",
            "Latency": "",
            "PipelineII": "",
            "PipelineDepthMin": "4",
            "PipelineDepthMax": "118",
            "PipelineDepth": "4 ~ 118"
          },
          {
            "Name": "Loop 24",
            "TripCount": "",
            "Latency": "",
            "PipelineII": "",
            "PipelineDepthMin": "4",
            "PipelineDepthMax": "118",
            "PipelineDepth": "4 ~ 118"
          },
          {
            "Name": "Loop 25",
            "TripCount": "",
            "Latency": "",
            "PipelineII": "",
            "PipelineDepthMin": "4",
            "PipelineDepthMax": "118",
            "PipelineDepth": "4 ~ 118"
          },
          {
            "Name": "Loop 26",
            "TripCount": "",
            "Latency": "",
            "PipelineII": "",
            "PipelineDepthMin": "4",
            "PipelineDepthMax": "118",
            "PipelineDepth": "4 ~ 118"
          },
          {
            "Name": "Loop 27",
            "TripCount": "",
            "Latency": "",
            "PipelineII": "",
            "PipelineDepthMin": "4",
            "PipelineDepthMax": "118",
            "PipelineDepth": "4 ~ 118"
          },
          {
            "Name": "Loop 28",
            "TripCount": "",
            "Latency": "",
            "PipelineII": "",
            "PipelineDepthMin": "4",
            "PipelineDepthMax": "118",
            "PipelineDepth": "4 ~ 118"
          },
          {
            "Name": "Loop 29",
            "TripCount": "",
            "Latency": "",
            "PipelineII": "",
            "PipelineDepthMin": "4",
            "PipelineDepthMax": "118",
            "PipelineDepth": "4 ~ 118"
          },
          {
            "Name": "Loop 30",
            "TripCount": "",
            "Latency": "",
            "PipelineII": "",
            "PipelineDepthMin": "4",
            "PipelineDepthMax": "118",
            "PipelineDepth": "4 ~ 118"
          },
          {
            "Name": "Loop 31",
            "TripCount": "",
            "Latency": "",
            "PipelineII": "",
            "PipelineDepthMin": "4",
            "PipelineDepthMax": "118",
            "PipelineDepth": "4 ~ 118"
          },
          {
            "Name": "Loop 32",
            "TripCount": "",
            "Latency": "",
            "PipelineII": "",
            "PipelineDepthMin": "4",
            "PipelineDepthMax": "118",
            "PipelineDepth": "4 ~ 118"
          },
          {
            "Name": "Loop 33",
            "TripCount": "",
            "Latency": "",
            "PipelineII": "",
            "PipelineDepthMin": "4",
            "PipelineDepthMax": "118",
            "PipelineDepth": "4 ~ 118"
          },
          {
            "Name": "Loop 34",
            "TripCount": "",
            "Latency": "",
            "PipelineII": "",
            "PipelineDepthMin": "4",
            "PipelineDepthMax": "118",
            "PipelineDepth": "4 ~ 118"
          },
          {
            "Name": "Loop 35",
            "TripCount": "",
            "Latency": "",
            "PipelineII": "",
            "PipelineDepthMin": "4",
            "PipelineDepthMax": "118",
            "PipelineDepth": "4 ~ 118"
          },
          {
            "Name": "Loop 36",
            "TripCount": "",
            "Latency": "",
            "PipelineII": "",
            "PipelineDepthMin": "4",
            "PipelineDepthMax": "118",
            "PipelineDepth": "4 ~ 118"
          },
          {
            "Name": "Loop 37",
            "TripCount": "",
            "Latency": "",
            "PipelineII": "",
            "PipelineDepthMin": "4",
            "PipelineDepthMax": "118",
            "PipelineDepth": "4 ~ 118"
          },
          {
            "Name": "Loop 38",
            "TripCount": "",
            "Latency": "",
            "PipelineII": "",
            "PipelineDepthMin": "4",
            "PipelineDepthMax": "118",
            "PipelineDepth": "4 ~ 118"
          }
        ],
        "Area": {
          "BRAM_18K": "6",
          "FF": "13965",
          "LUT": "399876",
          "URAM": "0",
          "DSP48E": "0"
        }
      },
      "pqcrystals_dilithium_24": {
        "Latency": {
          "LatencyBest": "",
          "LatencyAvg": "",
          "LatencyWorst": "",
          "PipelineII": "",
          "PipelineDepth": "",
          "PipelineType": "none"
        },
        "Timing": {
          "Target": "10000.00",
          "Uncertainty": "1250.00",
          "Estimate": "56.962"
        },
        "Loops": [{
            "Name": "Loop 1",
            "TripCount": "",
            "Latency": "",
            "PipelineII": "",
            "PipelineDepth": "",
            "Loops": [{
                "Name": "Loop 1.1",
                "TripCount": "",
                "Latency": "",
                "PipelineII": "",
                "PipelineDepth": "3"
              }]
          }],
        "Area": {
          "BRAM_18K": "1",
          "DSP48E": "1818",
          "FF": "16248",
          "LUT": "61615",
          "URAM": "0"
        }
      },
      "pqcrystals_dilithium_13": {
        "Latency": {
          "LatencyBest": "128",
          "LatencyAvg": "128",
          "LatencyWorst": "128",
          "PipelineII": "128",
          "PipelineDepth": "",
          "PipelineType": "none"
        },
        "Timing": {
          "Target": "10000.00",
          "Uncertainty": "1250.00",
          "Estimate": "32.165"
        },
        "Area": {
          "DSP48E": "1036",
          "FF": "137",
          "LUT": "16955",
          "BRAM_18K": "0",
          "URAM": "0"
        }
      },
      "pqcrystals_dilithium_22": {
        "Latency": {
          "LatencyBest": "255",
          "LatencyAvg": "255",
          "LatencyWorst": "255",
          "PipelineII": "255",
          "PipelineDepth": "",
          "PipelineType": "none"
        },
        "Timing": {
          "Target": "10000.00",
          "Uncertainty": "1250.00",
          "Estimate": "7.724"
        },
        "Area": {
          "FF": "8396",
          "LUT": "24857",
          "BRAM_18K": "0",
          "DSP48E": "0",
          "URAM": "0"
        }
      },
      "pqcrystals_dilithium_18": {
        "Latency": {
          "LatencyBest": "128",
          "LatencyAvg": "128",
          "LatencyWorst": "128",
          "PipelineII": "128",
          "PipelineDepth": "",
          "PipelineType": "none"
        },
        "Timing": {
          "Target": "10000.00",
          "Uncertainty": "1250.00",
          "Estimate": "9.463"
        },
        "Area": {
          "FF": "406",
          "LUT": "28626",
          "BRAM_18K": "0",
          "DSP48E": "0",
          "URAM": "0"
        }
      },
      "pqcrystals_dilithium_11": {
        "Latency": {
          "LatencyBest": "255",
          "LatencyAvg": "255",
          "LatencyWorst": "255",
          "PipelineII": "255",
          "PipelineDepth": "",
          "PipelineType": "none"
        },
        "Timing": {
          "Target": "10000.00",
          "Uncertainty": "1250.00",
          "Estimate": "7.724"
        },
        "Area": {
          "FF": "8396",
          "LUT": "24857",
          "BRAM_18K": "0",
          "DSP48E": "0",
          "URAM": "0"
        }
      },
      "pqcrystals_dilithium_6": {
        "Latency": {
          "LatencyBest": "131",
          "LatencyAvg": "390",
          "LatencyWorst": "519",
          "PipelineIIMin": "131",
          "PipelineIIMax": "519",
          "PipelineII": "131 ~ 519",
          "PipelineDepth": "",
          "PipelineType": "none"
        },
        "Timing": {
          "Target": "10000.00",
          "Uncertainty": "1250.00",
          "Estimate": "10.813"
        },
        "Area": {
          "FF": "420",
          "LUT": "28750",
          "BRAM_18K": "0",
          "DSP48E": "0",
          "URAM": "0"
        }
      },
      "pqcrystals_dilithium_27": {
        "Latency": {
          "LatencyBest": "0",
          "LatencyAvg": "0",
          "LatencyWorst": "0",
          "PipelineII": "0",
          "PipelineDepth": "",
          "PipelineType": "none"
        },
        "Timing": {
          "Target": "10000.00",
          "Uncertainty": "1250.00",
          "Estimate": "2.911"
        },
        "Area": {
          "FF": "0",
          "LUT": "80",
          "BRAM_18K": "0",
          "DSP48E": "0",
          "URAM": "0"
        }
      },
      "pqcrystals_dilithium_16": {
        "Latency": {
          "LatencyBest": "128",
          "LatencyAvg": "128",
          "LatencyWorst": "128",
          "PipelineII": "128",
          "PipelineDepth": "",
          "PipelineType": "none"
        },
        "Timing": {
          "Target": "10000.00",
          "Uncertainty": "1250.00",
          "Estimate": "20.442"
        },
        "Area": {
          "FF": "524",
          "LUT": "17512",
          "BRAM_18K": "0",
          "DSP48E": "0",
          "URAM": "0"
        }
      },
      "pqcrystals_dilithium_4": {
        "Latency": {
          "LatencyBest": "288",
          "LatencyAvg": "288",
          "LatencyWorst": "288",
          "PipelineII": "288",
          "PipelineDepth": "",
          "PipelineType": "none"
        },
        "Timing": {
          "Target": "10000.00",
          "Uncertainty": "1250.00",
          "Estimate": "8.524"
        },
        "Area": {
          "FF": "367",
          "LUT": "21300",
          "BRAM_18K": "0",
          "DSP48E": "0",
          "URAM": "0"
        }
      },
      "pqcrystals_dilithium_23": {
        "Latency": {
          "LatencyBest": "2227",
          "LatencyAvg": "2227",
          "LatencyWorst": "2227",
          "PipelineII": "2227",
          "PipelineDepth": "",
          "PipelineType": "none"
        },
        "Timing": {
          "Target": "10000.00",
          "Uncertainty": "1250.00",
          "Estimate": "8.524"
        },
        "Area": {
          "FF": "10676",
          "LUT": "77221",
          "BRAM_18K": "0",
          "DSP48E": "0",
          "URAM": "0"
        }
      },
      "pqcrystals_dilithium_1": {
        "Latency": {
          "LatencyBest": "",
          "LatencyAvg": "",
          "LatencyWorst": "",
          "PipelineII": "",
          "PipelineDepth": "",
          "PipelineType": "none"
        },
        "Timing": {
          "Target": "10000.00",
          "Uncertainty": "1250.00",
          "Estimate": "83.112"
        },
        "Loops": [
          {
            "Name": "Loop 1",
            "TripCount": "6",
            "Latency": "30",
            "PipelineII": "",
            "PipelineDepth": "5"
          },
          {
            "Name": "Loop 2",
            "TripCount": "10",
            "Latency": "40",
            "PipelineII": "4",
            "PipelineDepth": "5"
          },
          {
            "Name": "Loop 3",
            "TripCount": "6",
            "Latency": "30",
            "PipelineII": "",
            "PipelineDepth": "5"
          },
          {
            "Name": "Loop 4",
            "TripCount": "",
            "Latency": "",
            "PipelineII": "",
            "PipelineDepth": "",
            "Loops": [
              {
                "Name": "Loop 4.1",
                "TripCount": "256",
                "Latency": "511",
                "PipelineII": "",
                "PipelineDepth": "2"
              },
              {
                "Name": "Loop 4.2",
                "TripCount": "256",
                "Latency": "511",
                "PipelineII": "",
                "PipelineDepth": "2"
              },
              {
                "Name": "Loop 4.3",
                "TripCount": "256",
                "Latency": "511",
                "PipelineII": "",
                "PipelineDepth": "2"
              },
              {
                "Name": "Loop 4.4",
                "TripCount": "256",
                "Latency": "511",
                "PipelineII": "",
                "PipelineDepth": "2"
              },
              {
                "Name": "Loop 4.5",
                "TripCount": "4",
                "Latency": "1028",
                "PipelineII": "",
                "PipelineDepth": "257"
              },
              {
                "Name": "Loop 4.6",
                "TripCount": "4",
                "Latency": "20",
                "PipelineII": "",
                "PipelineDepth": "5"
              }
            ]
          }
        ],
        "Area": {
          "BRAM_18K": "65",
          "DSP48E": "9884",
          "FF": "189503",
          "LUT": "2411855",
          "URAM": "0"
        }
      },
      "crypto_sign": {
        "Latency": {
          "LatencyBest": "",
          "LatencyAvg": "",
          "LatencyWorst": "",
          "PipelineII": "",
          "PipelineDepth": "",
          "PipelineType": "none"
        },
        "Timing": {
          "Target": "10000.00",
          "Uncertainty": "1250.00",
          "Estimate": "83.112"
        },
        "Loops": [{
            "Name": "Loop 1",
            "TripCount": "",
            "Latency": "",
            "PipelineII": "1",
            "PipelineDepth": "2"
          }],
        "Area": {
          "BRAM_18K": "65",
          "DSP48E": "9884",
          "FF": "189616",
          "LUT": "2412241",
          "URAM": "0"
        }
      }
    }
  },
  "Sdx": {
    "Target": "none",
    "ProfileOption": "0",
    "ProfileType": "none",
    "XO": "",
    "KernelName": "crypto_sign",
    "EnableXoSwEmu": "1"
  },
  "GenData": {
    "DataVersion": "0.2",
    "Time": "2023-04-09 23:20:41 IST",
    "ToolName": "vivado_hls",
    "ToolVersion": "2019.2"
  }
}
